musically/__init__.py
musically/arts.py
musically/config.py
musically/dev.py
musically/gen.py
musically/make.py
musically/musical.py
musically/setup_config.py
musically-1.1.0.dist-info/METADATA
musically-1.1.0.dist-info/WHEEL
musically-1.1.0.dist-info/entry_points.txt
musically-1.1.0.dist-info/top_level.txt
musically-1.1.0.dist-info/RECORD
