Metadata-Version: 2.2
Name: musically
Version: 1.1.0
Summary: A package for automating music-related tasks via Telegram bot.
Home-page: https://github.com/ankit-chaubey/musically
Author: Ankit Chaubey
Author-email: m.ankitchaubey@gmail.com
Classifier: Programming Language :: Python :: 3
Classifier: License :: OSI Approved :: MIT License
Classifier: Operating System :: OS Independent
Requires-Python: >=3.10
Requires-Dist: pyrogram
Requires-Dist: tqdm
Requires-Dist: colorama
Requires-Dist: mutagen
Requires-Dist: requests
Requires-Dist: TgCrypto
Dynamic: author
Dynamic: author-email
Dynamic: classifier
Dynamic: description
Dynamic: description-content-type
Dynamic: home-page
Dynamic: requires-dist
Dynamic: requires-python
Dynamic: summary
